guillotina_linkintegrity/__init__.py
guillotina_linkintegrity/api.py
guillotina_linkintegrity/cache.py
guillotina_linkintegrity/install.py
guillotina_linkintegrity/storage.py
guillotina_linkintegrity/subscribers.py
guillotina_linkintegrity/utils.py
guillotina_linkintegrity/tests/__init__.py
guillotina_linkintegrity/tests/conftest.py
guillotina_linkintegrity/tests/fixtures.py
guillotina_linkintegrity/tests/test_api.py
guillotina_linkintegrity/tests/test_li.py
guillotina_linkintegrity-6.0.0.dist-info/METADATA
guillotina_linkintegrity-6.0.0.dist-info/WHEEL
guillotina_linkintegrity-6.0.0.dist-info/top_level.txt
guillotina_linkintegrity-6.0.0.dist-info/RECORD
