Metadata-Version: 2.1
Name: guillotina-linkintegrity
Version: 6.0.0
Summary: Link integrity support for guillotina
Home-page: https://github.com/guillotinaweb/guillotina_linkintegrity
Author: Nathan Van Gheem
Author-email: vangheem@gmail.com
License: UNKNOWN
Platform: UNKNOWN
Classifier: License :: OSI Approved :: BSD License
Classifier: Intended Audience :: Developers
Classifier: Topic :: Internet :: WWW/HTTP
Classifier: Programming Language :: Python :: 3.6
Classifier: Programming Language :: Python :: 3.7
Classifier: Topic :: Software Development :: Libraries :: Python Modules
Requires-Dist: guillotina (>=6.3.0)
Requires-Dist: aioredis
Requires-Dist: pypika
Requires-Dist: lxml
Provides-Extra: test
Requires-Dist: pytest (>=3.8.0) ; extra == 'test'
Requires-Dist: pytest-asyncio (>=0.10.0) ; extra == 'test'
Requires-Dist: pytest-cov (>=2.4.0) ; extra == 'test'
Requires-Dist: pytest-runner (>=2.11.1) ; extra == 'test'
Requires-Dist: backoff (>=1.10.0) ; extra == 'test'
Requires-Dist: docker (>=2.2.1) ; extra == 'test'
Requires-Dist: docker-pycreds (>=0.2.1) ; extra == 'test'
Requires-Dist: psycopg2-binary ; extra == 'test'
Requires-Dist: pytest-docker-fixtures ; extra == 'test'
Requires-Dist: async-asgi-testclient ; extra == 'test'
Requires-Dist: aiohttp (<4.0.0,>=3.6.0) ; extra == 'test'
Requires-Dist: aioredis (>=1.3.1) ; extra == 'test'
Requires-Dist: prometheus-client ; extra == 'test'
